setup.cfg
setup.py
apsd/__init__.py
apsd/inn.py
apsd.egg-info/PKG-INFO
apsd.egg-info/SOURCES.txt
apsd.egg-info/dependency_links.txt
apsd.egg-info/top_level.txt