Metadata-Version: 2.1
Name: apsd
Version: 0.53
Summary: Package Description
Home-page: UNKNOWN
Author-email: inspiredbycatdreams@gmail.com
License: UNKNOWN
Platform: UNKNOWN
